hyperthought/__init__.py
hyperthought/auth.py
hyperthought/metadata.py
hyperthought/utils.py
hyperthought/api/__init__.py
hyperthought/api/base.py
hyperthought/api/common.py
hyperthought/api/files.py
hyperthought/api/metatron.py
hyperthought/api/search.py
hyperthought/api/workspaces.py
hyperthought/api/workflow/__init__.py
hyperthought/api/workflow/_construction/__init__.py
hyperthought/api/workflow/_construction/xml_generation.py
hyperthought/api/workflow/_construction/algorithms/__init__.py
hyperthought/api/workflow/_construction/algorithms/coordinates.py
hyperthought/api/workflow/_construction/algorithms/root.py
hyperthought/api/workflow/_construction/algorithms/unionfind.py
hyperthought/parsers/__init__.py
hyperthought/parsers/_ayasdi.py
hyperthought/parsers/_centerstreet.py
hyperthought/parsers/_craic.py
hyperthought/parsers/_dln.py
hyperthought/parsers/_eids.py
hyperthought/parsers/_fei_tiff.py
hyperthought/parsers/_genericjson.py
hyperthought/parsers/_genericxml.py
hyperthought/parsers/_hyperspy.py
hyperthought/parsers/_midas.py
hyperthought/parsers/_nsidat.py
hyperthought/parsers/_picard.py
hyperthought/parsers/base.py
hyperthought/parsers/utils/__init__.py
hyperthought/parsers/utils/flatten.py
hyperthought-1.2.2.dist-info/LICENSE
hyperthought-1.2.2.dist-info/METADATA
hyperthought-1.2.2.dist-info/WHEEL
hyperthought-1.2.2.dist-info/top_level.txt
hyperthought-1.2.2.dist-info/RECORD
