Metadata-Version: 2.1
Name: hyperthought
Version: 1.2.2
Summary: Wrappers for HyperThought® API
Home-page: https://gitlab.com/hyperthought/hyperthought-easy-api
Author: Jason Thiese
Author-email: jasonthiese@gmail.com
License: UNKNOWN
Project-URL: Bug Tracker, https://gitlab.com/hyperthought/hyperthought-easy-api/issues
Platform: UNKNOWN
Classifier: Programming Language :: Python :: 3
Classifier: License :: OSI Approved :: MIT License
Classifier: Operating System :: OS Independent
Requires-Python: >=3.6
License-File: LICENSE
